st_mathlive/__init__.py
st_mathlive/frontend/build/1_index.html
st_mathlive/frontend/build/asset-manifest.json
st_mathlive/frontend/build/bootstrap.min.css
st_mathlive/frontend/build/index.html
st_mathlive/frontend/build/theme.min.css
st_mathlive/frontend/build/static/css/main.babaa262.css
st_mathlive/frontend/build/static/css/main.babaa262.css.map
st_mathlive/frontend/build/static/js/main.32ee94a0.js
st_mathlive/frontend/build/static/js/main.32ee94a0.js.LICENSE.txt
st_mathlive/frontend/build/static/js/main.32ee94a0.js.map
streamlit_mathlive-0.0.3.dist-info/LICENSE
streamlit_mathlive-0.0.3.dist-info/METADATA
streamlit_mathlive-0.0.3.dist-info/WHEEL
streamlit_mathlive-0.0.3.dist-info/top_level.txt
streamlit_mathlive-0.0.3.dist-info/RECORD
